setup.py
flask_args/__init__.py
flask_args.egg-info/PKG-INFO
flask_args.egg-info/SOURCES.txt
flask_args.egg-info/dependency_links.txt
flask_args.egg-info/requires.txt
flask_args.egg-info/top_level.txt