Metadata-Version: 1.0
Name: flask-args
Version: 0.3.0
Summary: auto type convertion for flask.request.form/args/values
Home-page: UNKNOWN
Author: UNKNOWN
Author-email: UNKNOWN
License: MIT
Platform: UNKNOWN
